slither_app/__init__.py
slither_app/slither_app.py
slither_app-0.0.11.dist-info/LICENSE
slither_app-0.0.11.dist-info/METADATA
slither_app-0.0.11.dist-info/WHEEL
slither_app-0.0.11.dist-info/top_level.txt
slither_app-0.0.11.dist-info/RECORD
