Metadata-Version: 2.1
Name: slither-app
Version: 0.0.11
Summary: A python companion to run_app
Author-email: Adam Otruba <adam.otruba@shmu.sk>
License: DO WHAT THE FUCK YOU WANT TO PUBLIC LICENSE 
Classifier: Programming Language :: Python :: 3
Classifier: Operating System :: OS Independent
Requires-Python: >=3.7
License-File: LICENSE
